arafkhan_hello/__init__.py
arafkhan_hello/main.py
arafkhan_hello-0.4.dist-info/METADATA
arafkhan_hello-0.4.dist-info/WHEEL
arafkhan_hello-0.4.dist-info/entry_points.txt
arafkhan_hello-0.4.dist-info/top_level.txt
arafkhan_hello-0.4.dist-info/RECORD
