Metadata-Version: 2.1
Name: arafkhan-hello
Version: 0.4
Summary: Simple Hello world package
Home-page: 
Author: Araf
Author-email: arafkhan565@gmail.com
